.gitignore
LICENSE
README.md
pyproject.toml
requirements.txt
rer.py
z_rer.egg-info/PKG-INFO
z_rer.egg-info/SOURCES.txt
z_rer.egg-info/dependency_links.txt
z_rer.egg-info/entry_points.txt
z_rer.egg-info/requires.txt
z_rer.egg-info/top_level.txt